astrophysics_toolset/__init__.py
astrophysics_toolset/astrophysics_toolset.py
astrophysics_toolset/cli.py
astrophysics_toolset/io/__init__.py
astrophysics_toolset/io/common.py
astrophysics_toolset/io/disperse.py
astrophysics_toolset/io/grafic.py
astrophysics_toolset/utilities/__init__.py
astrophysics_toolset/utilities/decorators.py
astrophysics_toolset/utilities/exceptions.py
astrophysics_toolset/utilities/periodicity.py
astrophysics_toolset/utilities/projections.py
astrophysics_toolset/utilities/types.py
astrophysics_toolset/utilities/tests/__init__.py
astrophysics_toolset/utilities/tests/test_periodicity.py
astrophysics_toolset/utilities/tests/test_projections.py
astrophysics_toolset-0.1.0.dist-info/AUTHORS.rst
astrophysics_toolset-0.1.0.dist-info/LICENSE
astrophysics_toolset-0.1.0.dist-info/METADATA
astrophysics_toolset-0.1.0.dist-info/WHEEL
astrophysics_toolset-0.1.0.dist-info/entry_points.txt
astrophysics_toolset-0.1.0.dist-info/top_level.txt
astrophysics_toolset-0.1.0.dist-info/RECORD
