Metadata-Version: 2.1
Name: astrophysics-toolset
Version: 0.1.0
Summary: Python package with some astrophysics-related stuff
Home-page: https://github.com/cphyc/astrophysics_toolset
Author: Corentin Cadiou
Author-email: c.cadiou@ucl.ac.uk
License: MIT license
Keywords: astrophysics_toolset
Platform: UNKNOWN
Classifier: Development Status :: 2 - Pre-Alpha
Classifier: Intended Audience :: Developers
Classifier: License :: OSI Approved :: MIT License
Classifier: Natural Language :: English
Classifier: Programming Language :: Python :: 3
Classifier: Programming Language :: Python :: 3.5
Classifier: Programming Language :: Python :: 3.6
Classifier: Programming Language :: Python :: 3.7
Classifier: Programming Language :: Python :: 3.8
Requires-Python: >=3.5
Requires-Dist: scipy (>=1.4.1)
Requires-Dist: numpy (>=1.0)
Requires-Dist: kaitaistruct
Requires-Dist: numba (>=0.40)
